has/__init__.py
has/has.py
has/test_has.py
has-0.0.4.dist-info/LICENSE
has-0.0.4.dist-info/METADATA
has-0.0.4.dist-info/WHEEL
has-0.0.4.dist-info/entry_points.txt
has-0.0.4.dist-info/top_level.txt
has-0.0.4.dist-info/RECORD
