Metadata-Version: 2.1
Name: has
Version: 0.0.4
Summary: Hash array snapshot
Home-page: https://gitlab.com/timcogan/hash_array_snapshot
Author: Tim Cogan
Author-email: timothycogan@gmail.com
License: Apache
Platform: UNKNOWN
